amiyabot/__init__.py
amiyabot/signalHandler.py
amiyabot/typeIndexes.py
amiyabot/util.py
amiyabot/_assets/font/HarmonyOS_Sans_SC.ttf
amiyabot/_assets/font/font.css
amiyabot/_assets/markdown/template-dark.html
amiyabot/_assets/markdown/template.html
amiyabot/_assets/markdown/js/highlight.min.js
amiyabot/_assets/markdown/js/marked.min.js
amiyabot/_assets/markdown/js/vue.min.js
amiyabot/_assets/markdown/style/github-markdown-dark.css
amiyabot/_assets/markdown/style/github-markdown.css
amiyabot/_assets/markdown/style/highlight/vs.min.css
amiyabot/_assets/markdown/style/highlight/vs2015.min.css
amiyabot/adapters/__init__.py
amiyabot/adapters/apiProtocol.py
amiyabot/adapters/common.py
amiyabot/adapters/comwechat/__init__.py
amiyabot/adapters/comwechat/builder.py
amiyabot/adapters/comwechat/package.py
amiyabot/adapters/cqhttp/__init__.py
amiyabot/adapters/cqhttp/api.py
amiyabot/adapters/cqhttp/forwardMessage.py
amiyabot/adapters/kook/__init__.py
amiyabot/adapters/kook/api.py
amiyabot/adapters/kook/builder.py
amiyabot/adapters/kook/package.py
amiyabot/adapters/mirai/__init__.py
amiyabot/adapters/mirai/api.py
amiyabot/adapters/mirai/builder.py
amiyabot/adapters/mirai/forwardMessage.py
amiyabot/adapters/mirai/package.py
amiyabot/adapters/mirai/payload.py
amiyabot/adapters/onebot/__init__.py
amiyabot/adapters/onebot/v11/__init__.py
amiyabot/adapters/onebot/v11/api.py
amiyabot/adapters/onebot/v11/builder.py
amiyabot/adapters/onebot/v11/package.py
amiyabot/adapters/onebot/v12/__init__.py
amiyabot/adapters/onebot/v12/api.py
amiyabot/adapters/onebot/v12/builder.py
amiyabot/adapters/onebot/v12/package.py
amiyabot/adapters/tencent/__init__.py
amiyabot/adapters/tencent/qqGuild/__init__.py
amiyabot/adapters/tencent/qqGuild/api.py
amiyabot/adapters/tencent/qqGuild/builder.py
amiyabot/adapters/tencent/qqGuild/intents.py
amiyabot/adapters/tencent/qqGuild/model.py
amiyabot/adapters/tencent/qqGuild/package.py
amiyabot/adapters/test/__init__.py
amiyabot/adapters/test/builder.py
amiyabot_core_test-1.8.5.90.dist-info/LICENSE
amiyabot_core_test-1.8.5.90.dist-info/METADATA
amiyabot_core_test-1.8.5.90.dist-info/WHEEL
amiyabot_core_test-1.8.5.90.dist-info/top_level.txt
amiyabot_core_test-1.8.5.90.dist-info/RECORD
